pytelerdac/__init__.py
pytelerdac/rdac.cpython-36m-aarch64-linux-gnu.so
pytelerdac/client/__init__.py
pytelerdac/client/http_client.cpython-36m-aarch64-linux-gnu.so
pytelerdac/const/__init__.py
pytelerdac/const/public.cpython-36m-aarch64-linux-gnu.so
pytelerdac/utils/__init__.py
pytelerdac/utils/device_utils.cpython-36m-aarch64-linux-gnu.so
pytelerdac/utils/license_utils.cpython-36m-aarch64-linux-gnu.so
pytelerdac-0.4.0.dist-info/METADATA
pytelerdac-0.4.0.dist-info/WHEEL
pytelerdac-0.4.0.dist-info/top_level.txt
pytelerdac-0.4.0.dist-info/RECORD
