Metadata-Version: 2.1
Name: pytelerdac
Version: 0.4.0
Summary: Python Package for tele rdac client
Home-page: UNKNOWN
Author: imason
Author-email: moy7@chinatelecom.cn
License: UNKNOWN
Keywords: pytelerdac
Platform: UNKNOWN
Classifier: Programming Language :: Python :: 3
Classifier: License :: OSI Approved :: MIT License
Classifier: Operating System :: OS Independent
Requires-Python: >=3.6,
Requires-Dist: teleencrypt (>=0.1.3)
Requires-Dist: requests (>=2.27.1)
Requires-Dist: rsa (>=4.9)
